[
  {
    "id": "5ec8c3444c56192e7a5d056f69684762761cecd6",
    "title": "MoonPay Acquires AI Accounting Agent Maker Entendre",
    "link": "https://www.pymnts.com/news/acquiring/2026/moonpay-acquires-ai-accounting-agent-maker-entendre/",
    "message_html": "<b>MoonPay Acquires AI Accounting Agent Maker Entendre</b> <a href=\"https://www.pymnts.com/news/acquiring/2026/moonpay-acquires-ai-accounting-agent-maker-entendre/\">...</a>",
    "score": 35,
    "snippet": "Crypto payments company MoonPay has acquired Entendre, which makes artificial intelligence (AI) accounting agents for stablecoin firms. The purchase “extends MoonPay’s infrastructure into the financial operations layer,” the company said in a Monday (June 22) news release, adding artificial intellig",
    "matched_topics": [
      "Stablecoin adoption",
      "Crypto-native fintech launches"
    ],
    "tier": "medium",
    "post_to_x": false,
    "category": "infrastructure"
  }
]